odoo/addons/announcement/README.rst
odoo/addons/announcement/__init__.py
odoo/addons/announcement/__manifest__.py
odoo/addons/announcement/i18n/announcement.pot
odoo/addons/announcement/i18n/es.po
odoo/addons/announcement/migrations/13.0.2.0.0/noupdate_changes.xml
odoo/addons/announcement/migrations/13.0.2.0.0/post-migration.py
odoo/addons/announcement/models/__init__.py
odoo/addons/announcement/models/announcement.py
odoo/addons/announcement/models/ir_config_parameter.py
odoo/addons/announcement/models/res_users.py
odoo/addons/announcement/readme/CONFIGURE.rst
odoo/addons/announcement/readme/CONTRIBUTORS.rst
odoo/addons/announcement/readme/DESCRIPTION.rst
odoo/addons/announcement/readme/ROADMAP.rst
odoo/addons/announcement/readme/USAGE.rst
odoo/addons/announcement/security/announcement_security.xml
odoo/addons/announcement/security/ir.model.access.csv
odoo/addons/announcement/static/description/icon.png
odoo/addons/announcement/static/description/index.html
odoo/addons/announcement/static/src/js/announcement.js
odoo/addons/announcement/static/src/js/announcement_dialog.js
odoo/addons/announcement/static/src/xml/announcement.xml
odoo/addons/announcement/static/src/xml/announcement_dialog.xml
odoo/addons/announcement/templates/assets_backend.xml
odoo/addons/announcement/views/announcement_views.xml
odoo/addons/announcement/wizards/__init__.py
odoo/addons/announcement/wizards/read_announcement_wizard.py
odoo/addons/announcement/wizards/read_announcement_wizard.xml
odoo13_addon_announcement-13.0.2.1.0.dist-info/METADATA
odoo13_addon_announcement-13.0.2.1.0.dist-info/WHEEL
odoo13_addon_announcement-13.0.2.1.0.dist-info/top_level.txt
odoo13_addon_announcement-13.0.2.1.0.dist-info/RECORD
